odoo/addons/product_brand_multicompany/README.rst
odoo/addons/product_brand_multicompany/__init__.py
odoo/addons/product_brand_multicompany/__manifest__.py
odoo/addons/product_brand_multicompany/i18n/it.po
odoo/addons/product_brand_multicompany/i18n/product_brand_multicompany.pot
odoo/addons/product_brand_multicompany/models/__init__.py
odoo/addons/product_brand_multicompany/models/product_brand.py
odoo/addons/product_brand_multicompany/readme/CONTRIBUTORS.rst
odoo/addons/product_brand_multicompany/readme/DESCRIPTION.rst
odoo/addons/product_brand_multicompany/security/ir_rule.xml
odoo/addons/product_brand_multicompany/static/description/icon.png
odoo/addons/product_brand_multicompany/static/description/index.html
odoo/addons/product_brand_multicompany/tests/__init__.py
odoo/addons/product_brand_multicompany/tests/test_product_brand.py
odoo/addons/product_brand_multicompany/views/product_brand_view.xml
odoo14_addon_product_brand_multicompany-14.0.1.0.1.dev6.dist-info/METADATA
odoo14_addon_product_brand_multicompany-14.0.1.0.1.dev6.dist-info/WHEEL
odoo14_addon_product_brand_multicompany-14.0.1.0.1.dev6.dist-info/top_level.txt
odoo14_addon_product_brand_multicompany-14.0.1.0.1.dev6.dist-info/RECORD
